dpg_styleqs/__init__.py
dpg_styleqs/dpg_styleqs.py
dpg_styleqs/internal/add.py
dpg_styleqs/internal/image.py
dpg_styleqs/internal/layout.py
dpg_styleqs/internal/more.py
dpg_styleqs/internal/theme.py
dpg_styleqs-0.1.5.dist-info/licenses/LICENSE
dpg_styleqs-0.1.5.dist-info/METADATA
dpg_styleqs-0.1.5.dist-info/WHEEL
dpg_styleqs-0.1.5.dist-info/top_level.txt
dpg_styleqs-0.1.5.dist-info/RECORD
