Metadata-Version: 2.4
Name: dpg_styleqs
Version: 0.1.5
Summary: Module created for DearpyGui, contains layout for widgets, new themes and new features
Author-email: qsouhe <qsouhe@gmail.com>
License-Expression: MIT
Project-URL: Homepage, https://github.com/Qsouhe/dpg_styleqs
Classifier: Programming Language :: Python :: 3
Classifier: Operating System :: OS Independent
Requires-Python: >=3.13
License-File: LICENSE
Requires-Dist: dearpygui>=2.1.0
Requires-Dist: numpy>=2.3.2
Requires-Dist: pillow>=11.3.0
Dynamic: license-file
